rascal/__init__.py
rascal/analogs.py
rascal/analysis.py
rascal/indices.py
rascal/utils.py
rascal_ties-1.0.10.dist-info/METADATA
rascal_ties-1.0.10.dist-info/WHEEL
rascal_ties-1.0.10.dist-info/top_level.txt
rascal_ties-1.0.10.dist-info/RECORD
