Metadata-Version: 2.1
Name: rascal-ties
Version: 1.0.10
Summary: Open-source tool for climatological time series reconstruction and extension
Home-page: https://github.com/alvaro-gc95/RASCAL
Download-URL: https://github.com/alvaro-gc95/RASCAL
Author: Alvaro Gonzalez-Cervera
Author-email: Alvaro Gonzalez-Cervera <alvaro@intermet.es>
Project-URL: homepage, https://github.com/alvaro-gc95/RASCAL
Project-URL: documentation, https://rascalv100.readthedocs.io/en/latest/
Project-URL: repository, https://github.com/alvaro-gc95/RASCAL
Classifier: Programming Language :: Python :: 3
Classifier: License :: OSI Approved :: MIT License
Classifier: Operating System :: OS Independent
Requires-Python: ==3.10
Requires-Dist: numpy ==1.26.4
Requires-Dist: pandas ==2.2.1
Requires-Dist: dask ==2024.4.1
Requires-Dist: xarray ==2024.3.0
Requires-Dist: scipy ==1.13.0
Requires-Dist: tqdm ==4.65.0
Requires-Dist: scikit-learn ==1.4.1.post1
Requires-Dist: seaborn ==0.13.2
Requires-Dist: eofs ==1.4.1
Requires-Dist: matplotlib >=3.5.5
Requires-Dist: sphinx-rtd-theme >=1.2.2
Requires-Dist: sphinx >=7.3.7
Requires-Dist: sphinx-copybutton >=0.5.2
Requires-Dist: cfgrib ==0.9.12.0
Requires-Dist: netCDF4 ==1.7.0
